ddbcereal/__init__.py
ddbcereal/deserializing.py
ddbcereal/exceptions.py
ddbcereal/py.typed
ddbcereal/serializing.py
ddbcereal/types.py
ddbcereal-2.1.1.dist-info/LICENSE.txt
ddbcereal-2.1.1.dist-info/METADATA
ddbcereal-2.1.1.dist-info/WHEEL
ddbcereal-2.1.1.dist-info/top_level.txt
ddbcereal-2.1.1.dist-info/RECORD
