Metadata-Version: 2.1
Name: ddbcereal
Version: 2.1.1
Summary: UNKNOWN
Home-page: https://github.com/JustinTArthur/ddbcereal
Author: Justin Turner Arthur
Author-email: justinarthur@gmail.com
License: Apache License 2.0
Platform: UNKNOWN
Classifier: License :: OSI Approved :: Apache Software License
Classifier: Topic :: Database
Classifier: Topic :: Software Development :: Libraries
Classifier: Topic :: Software Development :: Libraries :: Python Modules
Classifier: Typing :: Typed
Requires-Python: >=3.6
License-File: LICENSE.txt
